{"definition_id":"5596d12f5e1d80c255000003","title":"ROCKEFELLER CENTER ","url_friendly_name":"rockefeller-center","Outbound Link":"http://www.rockefellercenter.com/","Latitude":"40.758937","Longitude":"-73.978638","image":{"url":"/assets/images/4232/original/WestHouse-NH-Rockefeller.jpg"},"category_id":["55a7af34226e50787b00001e"],"image_id":"4232","_delete_image":"0","Outbound-Link":"https://www.rockefellercenter.com/","seo_title":"ROCKEFELLER CENTER | WestHouse Hotel New York","seo_description":"From soaring views at Top of the Rock to NBC Studios tours and the iconic skating rink, Rockefeller Center offers an endless array of activities and events in a complex consisting of 19 buildings covering 22 acres between 48th Street and 51st Street.","contents":"<p id=\"mf75\"><b>45 Rockefeller Plaza\n</b><br><a id=\"mfa17\" class=\"\">212.332.6868\n</a><br><br>From soaring views at Top of the Rock to NBC Studios tours and the iconic skating rink, Rockefeller Center offers an endless array of activities and events in a complex consisting of 19 buildings covering 22 acres between 48th Street and 51st Street.</p>","definition":"","category":["55a7af34226e50787b00001e"]}